{"v":"5.7.4","fr":29.9700012207031,"ip":0,"op":75.0000030548126,"w":173,"h":156,"nm":"No_Instrument","ddd":0,"assets":[],"layers":[{"ddd":0,"ind":1,"ty":4,"nm":"Ins4 Outlines","sr":1,"ks":{"o":{"a":1,"k":[{"i":{"x":[0.833],"y":[0.833]},"o":{"x":[0.167],"y":[0.167]},"t":25,"s":[0]},{"t":49.0000019958109,"s":[100]}],"ix":11},"r":{"a":0,"k":0,"ix":10},"p":{"a":1,"k":[{"i":{"x":0.667,"y":1},"o":{"x":0.333,"y":0},"t":25,"s":[67.5,6,0],"to":[0,4.667,0],"ti":[0,-4.667,0]},{"t":49.0000019958109,"s":[67.5,34,0]}],"ix":2,"l":2},"a":{"a":0,"k":[47.75,10.25,0],"ix":1,"l":2},"s":{"a":0,"k":[100,100,100],"ix":6,"l":2}},"ao":0,"shapes":[{"ty":"gr","it":[{"ind":0,"ty":"sh","ix":1,"ks":{"a":0,"k":{"i":[[-1.657,0],[0,0],[0,-1.657],[1.657,0],[0,0],[0,1.657]],"o":[[0,0],[1.657,0],[0,1.657],[0,0],[-1.657,0],[0,-1.657]],"v":[[-16,-3],[16,-3],[19,0],[16,3],[-16,3],[-19,0]],"c":true},"ix":2},"nm":"Path 1","mn":"ADBE Vector Shape - Group","hd":false},{"ty":"fl","c":{"a":0,"k":[0.835294177485,0.835294177485,0.835294177485,1],"ix":4},"o":{"a":0,"k":100,"ix":5},"r":1,"bm":0,"nm":"Fill 1","mn":"ADBE Vector Graphic - Fill","hd":false},{"ty":"tr","p":{"a":0,"k":[51.25,15.25],"ix":2},"a":{"a":0,"k":[0,0],"ix":1},"s":{"a":0,"k":[100,100],"ix":3},"r":{"a":0,"k":0,"ix":6},"o":{"a":0,"k":100,"ix":7},"sk":{"a":0,"k":0,"ix":4},"sa":{"a":0,"k":0,"ix":5},"nm":"Transform"}],"nm":"Group 1","np":2,"cix":2,"bm":0,"ix":1,"mn":"ADBE Vector Group","hd":false},{"ty":"gr","it":[{"ind":0,"ty":"sh","ix":1,"ks":{"a":0,"k":{"i":[[-1.657,0],[0,0],[0,-1.657],[1.657,0],[0,0],[0,1.657]],"o":[[0,0],[1.657,0],[0,1.657],[0,0],[-1.657,0],[0,-1.657]],"v":[[-28.5,-3],[28.5,-3],[31.5,0],[28.5,3],[-28.5,3],[-31.5,0]],"c":true},"ix":2},"nm":"Path 1","mn":"ADBE Vector Shape - Group","hd":false},{"ty":"fl","c":{"a":0,"k":[0.835294177485,0.835294177485,0.835294177485,1],"ix":4},"o":{"a":0,"k":100,"ix":5},"r":1,"bm":0,"nm":"Fill 1","mn":"ADBE Vector Graphic - Fill","hd":false},{"ty":"tr","p":{"a":0,"k":[63.75,5.25],"ix":2},"a":{"a":0,"k":[0,0],"ix":1},"s":{"a":0,"k":[100,100],"ix":3},"r":{"a":0,"k":0,"ix":6},"o":{"a":0,"k":100,"ix":7},"sk":{"a":0,"k":0,"ix":4},"sa":{"a":0,"k":0,"ix":5},"nm":"Transform"}],"nm":"Group 2","np":2,"cix":2,"bm":0,"ix":2,"mn":"ADBE Vector Group","hd":false},{"ty":"gr","it":[{"ind":0,"ty":"sh","ix":1,"ks":{"a":0,"k":{"i":[[-1.104,0],[0,0],[0,-1.105],[0,0],[1.104,0],[0,0],[0,1.104],[0,0]],"o":[[0,0],[1.104,0],[0,0],[0,1.104],[0,0],[-1.104,0],[0,0],[0,-1.105]],"v":[[-8,-10],[8,-10],[10,-8],[10,8],[8,10],[-8,10],[-10,8],[-10,-8]],"c":true},"ix":2},"nm":"Path 1","mn":"ADBE Vector Shape - Group","hd":false},{"ty":"fl","c":{"a":0,"k":[0.835294177485,0.835294177485,0.835294177485,1],"ix":4},"o":{"a":0,"k":100,"ix":5},"r":1,"bm":0,"nm":"Fill 1","mn":"ADBE Vector Graphic - Fill","hd":false},{"ty":"tr","p":{"a":0,"k":[10.25,10.25],"ix":2},"a":{"a":0,"k":[0,0],"ix":1},"s":{"a":0,"k":[100,100],"ix":3},"r":{"a":0,"k":0,"ix":6},"o":{"a":0,"k":100,"ix":7},"sk":{"a":0,"k":0,"ix":4},"sa":{"a":0,"k":0,"ix":5},"nm":"Transform"}],"nm":"Group 3","np":2,"cix":2,"bm":0,"ix":3,"mn":"ADBE Vector Group","hd":false}],"ip":0,"op":899.000036617021,"st":0,"bm":0},{"ddd":0,"ind":2,"ty":4,"nm":"Ins1 Outlines","sr":1,"ks":{"o":{"a":0,"k":100,"ix":11},"r":{"a":0,"k":0,"ix":10},"p":{"a":1,"k":[{"i":{"x":0.667,"y":1},"o":{"x":0.333,"y":0},"t":27,"s":[67.5,34,0],"to":[0,7.333,0],"ti":[0,-7.333,0]},{"t":45.0000018328876,"s":[67.5,78,0]}],"ix":2,"l":2},"a":{"a":0,"k":[47.75,10.25,0],"ix":1,"l":2},"s":{"a":0,"k":[100,100,100],"ix":6,"l":2}},"ao":0,"shapes":[{"ty":"gr","it":[{"ind":0,"ty":"sh","ix":1,"ks":{"a":0,"k":{"i":[[-1.657,0],[0,0],[0,-1.657],[1.657,0],[0,0],[0,1.657]],"o":[[0,0],[1.657,0],[0,1.657],[0,0],[-1.657,0],[0,-1.657]],"v":[[-16,-3],[16,-3],[19,0],[16,3],[-16,3],[-19,0]],"c":true},"ix":2},"nm":"Path 1","mn":"ADBE Vector Shape - Group","hd":false},{"ty":"fl","c":{"a":1,"k":[{"i":{"x":[0.833],"y":[0.833]},"o":{"x":[0.167],"y":[0.167]},"t":0,"s":[0.835294177485,0.835294177485,0.835294177485,1]},{"i":{"x":[0.833],"y":[0.833]},"o":{"x":[0.167],"y":[0.167]},"t":25,"s":[0.835294177485,0.835294177485,0.835294177485,1]},{"t":45.0000018328876,"s":[0.949019610882,0.949019610882,0.949019610882,1]}],"ix":4},"o":{"a":0,"k":100,"ix":5},"r":1,"bm":0,"nm":"Fill 1","mn":"ADBE Vector Graphic - Fill","hd":false},{"ty":"tr","p":{"a":0,"k":[51.25,15.25],"ix":2},"a":{"a":0,"k":[0,0],"ix":1},"s":{"a":0,"k":[100,100],"ix":3},"r":{"a":0,"k":0,"ix":6},"o":{"a":0,"k":100,"ix":7},"sk":{"a":0,"k":0,"ix":4},"sa":{"a":0,"k":0,"ix":5},"nm":"Transform"}],"nm":"Group 1","np":2,"cix":2,"bm":0,"ix":1,"mn":"ADBE Vector Group","hd":false},{"ty":"gr","it":[{"ind":0,"ty":"sh","ix":1,"ks":{"a":0,"k":{"i":[[-1.657,0],[0,0],[0,-1.657],[1.657,0],[0,0],[0,1.657]],"o":[[0,0],[1.657,0],[0,1.657],[0,0],[-1.657,0],[0,-1.657]],"v":[[-28.5,-3],[28.5,-3],[31.5,0],[28.5,3],[-28.5,3],[-31.5,0]],"c":true},"ix":2},"nm":"Path 1","mn":"ADBE Vector Shape - Group","hd":false},{"ty":"fl","c":{"a":1,"k":[{"i":{"x":[0.833],"y":[0.833]},"o":{"x":[0.167],"y":[0.167]},"t":0,"s":[0.835294177485,0.835294177485,0.835294177485,1]},{"i":{"x":[0.833],"y":[0.833]},"o":{"x":[0.167],"y":[0.167]},"t":25,"s":[0.835294177485,0.835294177485,0.835294177485,1]},{"t":45.0000018328876,"s":[0.949019610882,0.949019610882,0.949019610882,1]}],"ix":4},"o":{"a":0,"k":100,"ix":5},"r":1,"bm":0,"nm":"Fill 1","mn":"ADBE Vector Graphic - Fill","hd":false},{"ty":"tr","p":{"a":0,"k":[63.75,5.25],"ix":2},"a":{"a":0,"k":[0,0],"ix":1},"s":{"a":0,"k":[100,100],"ix":3},"r":{"a":0,"k":0,"ix":6},"o":{"a":0,"k":100,"ix":7},"sk":{"a":0,"k":0,"ix":4},"sa":{"a":0,"k":0,"ix":5},"nm":"Transform"}],"nm":"Group 2","np":2,"cix":2,"bm":0,"ix":2,"mn":"ADBE Vector Group","hd":false},{"ty":"gr","it":[{"ind":0,"ty":"sh","ix":1,"ks":{"a":0,"k":{"i":[[-1.104,0],[0,0],[0,-1.105],[0,0],[1.104,0],[0,0],[0,1.104],[0,0]],"o":[[0,0],[1.104,0],[0,0],[0,1.104],[0,0],[-1.104,0],[0,0],[0,-1.105]],"v":[[-8,-10],[8,-10],[10,-8],[10,8],[8,10],[-8,10],[-10,8],[-10,-8]],"c":true},"ix":2},"nm":"Path 1","mn":"ADBE Vector Shape - Group","hd":false},{"ty":"fl","c":{"a":1,"k":[{"i":{"x":[0.833],"y":[0.833]},"o":{"x":[0.167],"y":[0.167]},"t":0,"s":[0.835294177485,0.835294177485,0.835294177485,1]},{"i":{"x":[0.833],"y":[0.833]},"o":{"x":[0.167],"y":[0.167]},"t":25,"s":[0.835294177485,0.835294177485,0.835294177485,1]},{"t":45.0000018328876,"s":[0.949019610882,0.949019610882,0.949019610882,1]}],"ix":4},"o":{"a":0,"k":100,"ix":5},"r":1,"bm":0,"nm":"Fill 1","mn":"ADBE Vector Graphic - Fill","hd":false},{"ty":"tr","p":{"a":0,"k":[10.25,10.25],"ix":2},"a":{"a":0,"k":[0,0],"ix":1},"s":{"a":0,"k":[100,100],"ix":3},"r":{"a":0,"k":0,"ix":6},"o":{"a":0,"k":100,"ix":7},"sk":{"a":0,"k":0,"ix":4},"sa":{"a":0,"k":0,"ix":5},"nm":"Transform"}],"nm":"Group 3","np":2,"cix":2,"bm":0,"ix":3,"mn":"ADBE Vector Group","hd":false}],"ip":0,"op":899.000036617021,"st":0,"bm":0},{"ddd":0,"ind":3,"ty":4,"nm":"Ins2 Outlines","sr":1,"ks":{"o":{"a":0,"k":100,"ix":11},"r":{"a":0,"k":0,"ix":10},"p":{"a":1,"k":[{"i":{"x":0.667,"y":1},"o":{"x":0.333,"y":0},"t":27,"s":[67.5,78,0],"to":[0,7.333,0],"ti":[0,-7.333,0]},{"t":45.0000018328876,"s":[67.5,122,0]}],"ix":2,"l":2},"a":{"a":0,"k":[47.75,10.25,0],"ix":1,"l":2},"s":{"a":0,"k":[100,100,100],"ix":6,"l":2}},"ao":0,"shapes":[{"ty":"gr","it":[{"ind":0,"ty":"sh","ix":1,"ks":{"a":0,"k":{"i":[[-1.657,0],[0,0],[0,-1.657],[1.657,0],[0,0],[0,1.656]],"o":[[0,0],[1.657,0],[0,1.656],[0,0],[-1.657,0],[0,-1.657]],"v":[[-16,-3],[16,-3],[19,0],[16,3],[-16,3],[-19,0]],"c":true},"ix":2},"nm":"Path 1","mn":"ADBE Vector Shape - Group","hd":false},{"ty":"fl","c":{"a":0,"k":[0.949019667682,0.949019667682,0.949019667682,1],"ix":4},"o":{"a":0,"k":100,"ix":5},"r":1,"bm":0,"nm":"Fill 1","mn":"ADBE Vector Graphic - Fill","hd":false},{"ty":"tr","p":{"a":0,"k":[51.25,15.25],"ix":2},"a":{"a":0,"k":[0,0],"ix":1},"s":{"a":0,"k":[100,100],"ix":3},"r":{"a":0,"k":0,"ix":6},"o":{"a":0,"k":100,"ix":7},"sk":{"a":0,"k":0,"ix":4},"sa":{"a":0,"k":0,"ix":5},"nm":"Transform"}],"nm":"Group 1","np":2,"cix":2,"bm":0,"ix":1,"mn":"ADBE Vector Group","hd":false},{"ty":"gr","it":[{"ind":0,"ty":"sh","ix":1,"ks":{"a":0,"k":{"i":[[-1.657,0],[0,0],[0,-1.657],[1.657,0],[0,0],[0,1.657]],"o":[[0,0],[1.657,0],[0,1.657],[0,0],[-1.657,0],[0,-1.657]],"v":[[-28.5,-3],[28.5,-3],[31.5,0],[28.5,3],[-28.5,3],[-31.5,0]],"c":true},"ix":2},"nm":"Path 1","mn":"ADBE Vector Shape - Group","hd":false},{"ty":"fl","c":{"a":0,"k":[0.949019667682,0.949019667682,0.949019667682,1],"ix":4},"o":{"a":0,"k":100,"ix":5},"r":1,"bm":0,"nm":"Fill 1","mn":"ADBE Vector Graphic - Fill","hd":false},{"ty":"tr","p":{"a":0,"k":[63.75,5.25],"ix":2},"a":{"a":0,"k":[0,0],"ix":1},"s":{"a":0,"k":[100,100],"ix":3},"r":{"a":0,"k":0,"ix":6},"o":{"a":0,"k":100,"ix":7},"sk":{"a":0,"k":0,"ix":4},"sa":{"a":0,"k":0,"ix":5},"nm":"Transform"}],"nm":"Group 2","np":2,"cix":2,"bm":0,"ix":2,"mn":"ADBE Vector Group","hd":false},{"ty":"gr","it":[{"ind":0,"ty":"sh","ix":1,"ks":{"a":0,"k":{"i":[[-1.104,0],[0,0],[0,-1.105],[0,0],[1.104,0],[0,0],[0,1.104],[0,0]],"o":[[0,0],[1.104,0],[0,0],[0,1.104],[0,0],[-1.104,0],[0,0],[0,-1.105]],"v":[[-8,-10],[8,-10],[10,-8],[10,8],[8,10],[-8,10],[-10,8],[-10,-8]],"c":true},"ix":2},"nm":"Path 1","mn":"ADBE Vector Shape - Group","hd":false},{"ty":"fl","c":{"a":0,"k":[0.949019667682,0.949019667682,0.949019667682,1],"ix":4},"o":{"a":0,"k":100,"ix":5},"r":1,"bm":0,"nm":"Fill 1","mn":"ADBE Vector Graphic - Fill","hd":false},{"ty":"tr","p":{"a":0,"k":[10.25,10.25],"ix":2},"a":{"a":0,"k":[0,0],"ix":1},"s":{"a":0,"k":[100,100],"ix":3},"r":{"a":0,"k":0,"ix":6},"o":{"a":0,"k":100,"ix":7},"sk":{"a":0,"k":0,"ix":4},"sa":{"a":0,"k":0,"ix":5},"nm":"Transform"}],"nm":"Group 3","np":2,"cix":2,"bm":0,"ix":3,"mn":"ADBE Vector Group","hd":false}],"ip":0,"op":899.000036617021,"st":0,"bm":0},{"ddd":0,"ind":4,"ty":4,"nm":"Ins3 Outlines","sr":1,"ks":{"o":{"a":0,"k":100,"ix":11},"r":{"a":0,"k":0,"ix":10},"p":{"a":1,"k":[{"i":{"x":0.667,"y":1},"o":{"x":0.333,"y":0},"t":27,"s":[67.5,122,0],"to":[-0.667,7.333,0],"ti":[0.667,-7.333,0]},{"t":45.0000018328876,"s":[63.5,166,0]}],"ix":2,"l":2},"a":{"a":0,"k":[47.75,10.25,0],"ix":1,"l":2},"s":{"a":1,"k":[{"i":{"x":[0.833,0.833,0.833],"y":[0.833,0.833,0.833]},"o":{"x":[0.167,0.167,0.167],"y":[0.167,0.167,0.167]},"t":0,"s":[100,100,100]},{"i":{"x":[0.833,0.833,0.833],"y":[0.833,0.833,0.833]},"o":{"x":[0.167,0.167,0.167],"y":[0.167,0.167,0.167]},"t":27,"s":[100,100,100]},{"t":45.0000018328876,"s":[90,90,100]}],"ix":6,"l":2}},"ao":0,"shapes":[{"ty":"gr","it":[{"ind":0,"ty":"sh","ix":1,"ks":{"a":0,"k":{"i":[[-1.657,0],[0,0],[0,-1.657],[1.657,0],[0,0],[0,1.656]],"o":[[0,0],[1.657,0],[0,1.656],[0,0],[-1.657,0],[0,-1.657]],"v":[[-16,-3],[16,-3],[19,0],[16,3],[-16,3],[-19,0]],"c":true},"ix":2},"nm":"Path 1","mn":"ADBE Vector Shape - Group","hd":false},{"ty":"fl","c":{"a":0,"k":[0.949019670486,0.949019670486,0.949019670486,1],"ix":4},"o":{"a":0,"k":100,"ix":5},"r":1,"bm":0,"nm":"Fill 1","mn":"ADBE Vector Graphic - Fill","hd":false},{"ty":"tr","p":{"a":0,"k":[51.25,15.25],"ix":2},"a":{"a":0,"k":[0,0],"ix":1},"s":{"a":0,"k":[100,100],"ix":3},"r":{"a":0,"k":0,"ix":6},"o":{"a":0,"k":100,"ix":7},"sk":{"a":0,"k":0,"ix":4},"sa":{"a":0,"k":0,"ix":5},"nm":"Transform"}],"nm":"Group 1","np":2,"cix":2,"bm":0,"ix":1,"mn":"ADBE Vector Group","hd":false},{"ty":"gr","it":[{"ind":0,"ty":"sh","ix":1,"ks":{"a":0,"k":{"i":[[-1.657,0],[0,0],[0,-1.657],[1.657,0],[0,0],[0,1.656]],"o":[[0,0],[1.657,0],[0,1.656],[0,0],[-1.657,0],[0,-1.657]],"v":[[-28.5,-3],[28.5,-3],[31.5,0],[28.5,3],[-28.5,3],[-31.5,0]],"c":true},"ix":2},"nm":"Path 1","mn":"ADBE Vector Shape - Group","hd":false},{"ty":"fl","c":{"a":0,"k":[0.949019667682,0.949019667682,0.949019667682,1],"ix":4},"o":{"a":0,"k":100,"ix":5},"r":1,"bm":0,"nm":"Fill 1","mn":"ADBE Vector Graphic - Fill","hd":false},{"ty":"tr","p":{"a":0,"k":[63.75,5.25],"ix":2},"a":{"a":0,"k":[0,0],"ix":1},"s":{"a":0,"k":[100,100],"ix":3},"r":{"a":0,"k":0,"ix":6},"o":{"a":0,"k":100,"ix":7},"sk":{"a":0,"k":0,"ix":4},"sa":{"a":0,"k":0,"ix":5},"nm":"Transform"}],"nm":"Group 2","np":2,"cix":2,"bm":0,"ix":2,"mn":"ADBE Vector Group","hd":false},{"ty":"gr","it":[{"ind":0,"ty":"sh","ix":1,"ks":{"a":0,"k":{"i":[[-1.104,0],[0,0],[0,-1.104],[0,0],[1.104,0],[0,0],[0,1.104],[0,0]],"o":[[0,0],[1.104,0],[0,0],[0,1.104],[0,0],[-1.104,0],[0,0],[0,-1.104]],"v":[[-8,-10],[8,-10],[10,-8],[10,8],[8,10],[-8,10],[-10,8],[-10,-8]],"c":true},"ix":2},"nm":"Path 1","mn":"ADBE Vector Shape - Group","hd":false},{"ty":"fl","c":{"a":0,"k":[0.949019667682,0.949019667682,0.949019667682,1],"ix":4},"o":{"a":0,"k":100,"ix":5},"r":1,"bm":0,"nm":"Fill 1","mn":"ADBE Vector Graphic - Fill","hd":false},{"ty":"tr","p":{"a":0,"k":[10.25,10.25],"ix":2},"a":{"a":0,"k":[0,0],"ix":1},"s":{"a":0,"k":[100,100],"ix":3},"r":{"a":0,"k":0,"ix":6},"o":{"a":0,"k":100,"ix":7},"sk":{"a":0,"k":0,"ix":4},"sa":{"a":0,"k":0,"ix":5},"nm":"Transform"}],"nm":"Group 3","np":2,"cix":2,"bm":0,"ix":3,"mn":"ADBE Vector Group","hd":false}],"ip":0,"op":899.000036617021,"st":0,"bm":0},{"ddd":0,"ind":5,"ty":4,"nm":"add Outlines","sr":1,"ks":{"o":{"a":0,"k":100,"ix":11},"r":{"a":0,"k":0,"ix":10},"p":{"a":0,"k":[145,34,0],"ix":2,"l":2},"a":{"a":0,"k":[10.25,10.25,0],"ix":1,"l":2},"s":{"a":1,"k":[{"i":{"x":[0.667,0.667,0.667],"y":[1,1,1]},"o":{"x":[0.333,0.333,0.333],"y":[0,0,0]},"t":18,"s":[100,100,100]},{"i":{"x":[0.667,0.667,0.667],"y":[1,1,1]},"o":{"x":[0.333,0.333,0.333],"y":[0,0,0]},"t":23,"s":[70,70,100]},{"t":32.0000013033867,"s":[100,100,100]}],"ix":6,"l":2}},"ao":0,"shapes":[{"ty":"gr","it":[{"ind":0,"ty":"sh","ix":1,"ks":{"a":0,"k":{"i":[[0,0],[0,0],[0,0],[0.121,0],[0,0],[0,-0.122],[0,0],[0,0],[0,0],[0,-0.121],[0,0],[0,0],[-0.121,0],[0,0],[0,0],[-0.121,0],[0,0],[0,0.121],[0,0],[0,0],[0,0.122],[0,0],[0.121,0.001]],"o":[[0,0],[0,0],[0,-0.122],[0,0],[-0.121,0],[0,0],[0,0],[0,0],[-0.121,0],[0,0],[0,0],[0,0.122],[0,0],[0,0],[0,0.121],[0,0],[0.121,0],[0,0],[0,0],[0.121,0],[0,0],[0.001,-0.121],[0,0]],"v":[[5.072,-0.662],[0.662,-0.662],[0.662,-5.072],[0.441,-5.292],[-0.441,-5.292],[-0.661,-5.072],[-0.661,-5.071],[-0.661,-0.661],[-5.073,-0.661],[-5.292,-0.441],[-5.292,-0.44],[-5.292,0.442],[-5.073,0.662],[-0.661,0.662],[-0.661,5.072],[-0.443,5.292],[0.441,5.292],[0.661,5.072],[0.661,0.662],[5.071,0.662],[5.291,0.442],[5.291,-0.44],[5.073,-0.662]],"c":true},"ix":2},"nm":"Path 1","mn":"ADBE Vector Shape - Group","hd":false},{"ty":"fl","c":{"a":0,"k":[1,1,1,1],"ix":4},"o":{"a":0,"k":100,"ix":5},"r":1,"bm":0,"nm":"Fill 1","mn":"ADBE Vector Graphic - Fill","hd":false},{"ty":"tr","p":{"a":0,"k":[10.542,10.542],"ix":2},"a":{"a":0,"k":[0,0],"ix":1},"s":{"a":0,"k":[100,100],"ix":3},"r":{"a":0,"k":0,"ix":6},"o":{"a":0,"k":100,"ix":7},"sk":{"a":0,"k":0,"ix":4},"sa":{"a":0,"k":0,"ix":5},"nm":"Transform"}],"nm":"Group 1","np":2,"cix":2,"bm":0,"ix":1,"mn":"ADBE Vector Group","hd":false},{"ty":"gr","it":[{"ind":0,"ty":"sh","ix":1,"ks":{"a":0,"k":{"i":[[-5.522,0],[0,0],[0,-5.523],[5.522,0],[0,5.522]],"o":[[0,0],[5.522,0],[0,5.522],[-5.522,0],[0,-5.523]],"v":[[0,-10],[0,-10],[10,0],[0,10],[-10,0]],"c":true},"ix":2},"nm":"Path 1","mn":"ADBE Vector Shape - Group","hd":false},{"ty":"fl","c":{"a":0,"k":[0.454901990704,0.807843197093,0.439215716194,1],"ix":4},"o":{"a":0,"k":100,"ix":5},"r":1,"bm":0,"nm":"Fill 1","mn":"ADBE Vector Graphic - Fill","hd":false},{"ty":"tr","p":{"a":0,"k":[10.25,10.25],"ix":2},"a":{"a":0,"k":[0,0],"ix":1},"s":{"a":0,"k":[100,100],"ix":3},"r":{"a":0,"k":0,"ix":6},"o":{"a":0,"k":100,"ix":7},"sk":{"a":0,"k":0,"ix":4},"sa":{"a":0,"k":0,"ix":5},"nm":"Transform"}],"nm":"Group 2","np":2,"cix":2,"bm":0,"ix":2,"mn":"ADBE Vector Group","hd":false}],"ip":0,"op":899.000036617021,"st":0,"bm":0},{"ddd":0,"ind":6,"ty":4,"nm":"background Outlines","sr":1,"ks":{"o":{"a":0,"k":100,"ix":11},"r":{"a":0,"k":0,"ix":10},"p":{"a":0,"k":[86.5,78,0],"ix":2,"l":2},"a":{"a":0,"k":[86.75,78.25,0],"ix":1,"l":2},"s":{"a":0,"k":[100,100,100],"ix":6,"l":2}},"ao":0,"shapes":[{"ty":"gr","it":[{"ind":0,"ty":"sh","ix":1,"ks":{"a":0,"k":{"i":[[-5.523,0],[0,0],[0,-5.523],[0,0],[5.522,0],[0,0],[0,5.522],[0,0]],"o":[[0,0],[5.522,0],[0,0],[0,5.522],[0,0],[-5.523,0],[0,0],[0,-5.523]],"v":[[-76.5,-78],[76.5,-78],[86.5,-68],[86.5,68],[76.5,78],[-76.5,78],[-86.5,68],[-86.5,-68]],"c":true},"ix":2},"nm":"Path 1","mn":"ADBE Vector Shape - Group","hd":false},{"ty":"fl","c":{"a":0,"k":[1,1,1,1],"ix":4},"o":{"a":0,"k":100,"ix":5},"r":1,"bm":0,"nm":"Fill 1","mn":"ADBE Vector Graphic - Fill","hd":false},{"ty":"tr","p":{"a":0,"k":[86.75,78.25],"ix":2},"a":{"a":0,"k":[0,0],"ix":1},"s":{"a":0,"k":[100,100],"ix":3},"r":{"a":0,"k":0,"ix":6},"o":{"a":0,"k":100,"ix":7},"sk":{"a":0,"k":0,"ix":4},"sa":{"a":0,"k":0,"ix":5},"nm":"Transform"}],"nm":"Group 1","np":4,"cix":2,"bm":0,"ix":1,"mn":"ADBE Vector Group","hd":false}],"ip":0,"op":899.000036617021,"st":0,"bm":0}],"markers":[]}